oasisx/__init__.py
oasisx/__main__.py
oasisx/bcs.py
oasisx/fracstep.py
oasisx/function.py
oasisx/ksp.py
oasisx/main.py
oasisx/mesh.py
oasisx-1.3.0.dist-info/licenses/LICENSE
oasisx-1.3.0.dist-info/METADATA
oasisx-1.3.0.dist-info/WHEEL
oasisx-1.3.0.dist-info/entry_points.txt
oasisx-1.3.0.dist-info/top_level.txt
oasisx-1.3.0.dist-info/RECORD
