Metadata-Version: 2.4
Name: OasisX
Version: 1.3.0
Summary: A modern implementation of Oasis
Author-email: "Jørgen S. Dokken" <dokken@simula.no>
License: MIT License
Requires-Python: >=3.9
License-File: LICENSE
Requires-Dist: numpy
Requires-Dist: fenics-dolfinx<0.11,>=0.10
Provides-Extra: test
Requires-Dist: ruff; extra == "test"
Requires-Dist: mypy; extra == "test"
Requires-Dist: pytest; extra == "test"
Requires-Dist: pytest-cov; extra == "test"
Requires-Dist: isort; extra == "test"
Requires-Dist: scipy; extra == "test"
Provides-Extra: docs
Requires-Dist: jupyter-book; extra == "docs"
Requires-Dist: jupytext; extra == "docs"
Requires-Dist: seaborn; extra == "docs"
Requires-Dist: docutils; extra == "docs"
Provides-Extra: binder
Requires-Dist: jupyterlab; extra == "binder"
Requires-Dist: notebook; extra == "binder"
Dynamic: license-file
